hacmec/__init__.py
hacmec/client.py
hacmec/jws.py
hacmec/problem.py
hacmec/py.typed
hacmec/util.py
hacmec/http/__init__.py
hacmec/http/aiohttp.py
hacmec-0.0.3.dist-info/LICENSE
hacmec-0.0.3.dist-info/METADATA
hacmec-0.0.3.dist-info/WHEEL
hacmec-0.0.3.dist-info/top_level.txt
hacmec-0.0.3.dist-info/zip-safe
hacmec-0.0.3.dist-info/RECORD
